README.rst
setup.cfg
setup.py
adbs/__init__.py
adbs/core.py
adbs/nepday.py
adbs/nepnumber.py
adbs.egg-info/PKG-INFO
adbs.egg-info/SOURCES.txt
adbs.egg-info/dependency_links.txt
adbs.egg-info/top_level.txt