Metadata-Version: 1.0
Name: adbs
Version: 0.0.2
Summary: AD BS Converter
Home-page: https://github.com/techgaun/ad-bs-converter.py
Author: Samar Acharya
Author-email: samar+python@techgaun.com
License: Apache-2.0
Platform: UNKNOWN
